hpl/__init__.py
hpl/__main__.py
hpl/_unused.py
hpl/cli.py
hpl/errors.py
hpl/grammar.py
hpl/parser.py
hpl/rewrite.py
hpl/types.py
hpl/ast/__init__.py
hpl/ast/_unused.py
hpl/ast/base.py
hpl/ast/events.py
hpl/ast/expressions.py
hpl/ast/predicates.py
hpl/ast/properties.py
hpl/ast/specs.py
hpl/grammars/files.lark
hpl/grammars/predicates.lark
hpl/grammars/properties.lark
hpl/grammars/tokens.lark
hpl_specs-1.4.0.dist-info/LICENSE
hpl_specs-1.4.0.dist-info/METADATA
hpl_specs-1.4.0.dist-info/WHEEL
hpl_specs-1.4.0.dist-info/entry_points.txt
hpl_specs-1.4.0.dist-info/top_level.txt
hpl_specs-1.4.0.dist-info/RECORD
