Metadata-Version: 2.1
Name: hpl-specs
Version: 1.4.0
Summary: High-level Property Specification Language
Home-page: https://github.com/git-afsantos/hpl-specs
Author: André Santos
Author-email: haros.framework@gmail.com
License: MIT
Project-URL: Source, https://github.com/git-afsantos/hpl-specs/
Project-URL: Tracker, https://github.com/git-afsantos/hpl-specs/issues
Keywords: safety,liveness,property specification,specification language,parser,parsing,ast
Classifier: Development Status :: 5 - Production/Stable
Classifier: Intended Audience :: Developers
Classifier: Intended Audience :: Science/Research
Classifier: License :: OSI Approved :: MIT License
Classifier: Programming Language :: Python :: 3
Classifier: Programming Language :: Python :: 3.8
Classifier: Programming Language :: Python :: 3.9
Classifier: Programming Language :: Python :: 3.10
Classifier: Programming Language :: Python :: 3 :: Only
Classifier: Topic :: Scientific/Engineering
Classifier: Topic :: Software Development
Classifier: Topic :: Software Development :: Compilers
Classifier: Topic :: Software Development :: Libraries
Classifier: Topic :: Software Development :: Quality Assurance
Requires-Python: >=3.8, <4
License-File: LICENSE
Requires-Dist: attrs ~=23.0
Requires-Dist: lark ~=1.0
Requires-Dist: typeguard ~=4.1
Provides-Extra: dev
Requires-Dist: hypothesis[lark] ~=6.82 ; extra == 'dev'
Requires-Dist: pytest ; extra == 'dev'
Requires-Dist: tox ; extra == 'dev'
